pybehavior/__init__.py
pybehavior/models.py
pybehavior/tools.py
pybehavior-0.0.16.dist-info/METADATA
pybehavior-0.0.16.dist-info/WHEEL
pybehavior-0.0.16.dist-info/top_level.txt
pybehavior-0.0.16.dist-info/RECORD
