Metadata-Version: 2.1
Name: pybehavior
Version: 0.0.16
Summary: PyBehavior
Home-page: https://cwphs.ucsd.edu
Author: jup014
Author-email: jup014@ucsd.edu
License: MIT
Requires-Python: >=3
Requires-Dist: numpy
Requires-Dist: pandas
Requires-Dist: pyncei
